minecraft_motion_tools/__init__.py
minecraft_motion_tools/acceleration.py
minecraft_motion_tools/velocity.py
MinecraftMotionTools-1.8.7.dist-info/LICENSE
MinecraftMotionTools-1.8.7.dist-info/METADATA
MinecraftMotionTools-1.8.7.dist-info/WHEEL
MinecraftMotionTools-1.8.7.dist-info/top_level.txt
MinecraftMotionTools-1.8.7.dist-info/RECORD
