Metadata-Version: 2.1
Name: MinecraftMotionTools
Version: 1.8.7
Summary: A library to compute entities' motion in Minecraft.
Author: OrHy3
Project-URL: Homepage, https://github.com/OrHy3/MinecraftMotionTools
Project-URL: Issues, https://github.com/OrHy3/MinecraftMotionTools/issues
Requires-Python: >=3.8
License-File: LICENSE
Requires-Dist: scipy >=1.12.0
